GeeksforgeeksComputerNetworkLectureNotes/README.md
GeeksforgeeksComputerNetworkLectureNotes/__init__.py
GeeksforgeeksComputerNetworkLectureNotes/__main__.py
GeeksforgeeksComputerNetworkLectureNotes/file.epub
GeeksforgeeksComputerNetworkLectureNotes/index.html
GeeksforgeeksComputerNetworkLectureNotes/css/__init__.py
GeeksforgeeksComputerNetworkLectureNotes/css/annotations.css
GeeksforgeeksComputerNetworkLectureNotes/css/main.css
GeeksforgeeksComputerNetworkLectureNotes/css/normalize.css
GeeksforgeeksComputerNetworkLectureNotes/css/popup.css
GeeksforgeeksComputerNetworkLectureNotes/font/__init__.py
GeeksforgeeksComputerNetworkLectureNotes/font/fontello.eot
GeeksforgeeksComputerNetworkLectureNotes/font/fontello.svg
GeeksforgeeksComputerNetworkLectureNotes/font/fontello.ttf
GeeksforgeeksComputerNetworkLectureNotes/font/fontello.woff
GeeksforgeeksComputerNetworkLectureNotes/img/__init__.py
GeeksforgeeksComputerNetworkLectureNotes/img/annotator-glyph-sprite.png
GeeksforgeeksComputerNetworkLectureNotes/img/annotator-icon-sprite.png
GeeksforgeeksComputerNetworkLectureNotes/img/apple-touch-icon.png
GeeksforgeeksComputerNetworkLectureNotes/img/cancelfullscreen.png
GeeksforgeeksComputerNetworkLectureNotes/img/close.png
GeeksforgeeksComputerNetworkLectureNotes/img/fullscreen.png
GeeksforgeeksComputerNetworkLectureNotes/img/loader.gif
GeeksforgeeksComputerNetworkLectureNotes/img/menu-icon.png
GeeksforgeeksComputerNetworkLectureNotes/img/save.png
GeeksforgeeksComputerNetworkLectureNotes/img/saved.png
GeeksforgeeksComputerNetworkLectureNotes/img/settings-s.png
GeeksforgeeksComputerNetworkLectureNotes/img/settings.png
GeeksforgeeksComputerNetworkLectureNotes/img/star.png
GeeksforgeeksComputerNetworkLectureNotes/js/__init__.py
GeeksforgeeksComputerNetworkLectureNotes/js/epub.js
GeeksforgeeksComputerNetworkLectureNotes/js/epub.min.js
GeeksforgeeksComputerNetworkLectureNotes/js/epub.min.map
GeeksforgeeksComputerNetworkLectureNotes/js/hooks.min.js
geeksforgeeks_computer_network_lecture_notes-2024.3.3.0.dist-info/METADATA
geeksforgeeks_computer_network_lecture_notes-2024.3.3.0.dist-info/WHEEL
geeksforgeeks_computer_network_lecture_notes-2024.3.3.0.dist-info/entry_points.txt
geeksforgeeks_computer_network_lecture_notes-2024.3.3.0.dist-info/top_level.txt
geeksforgeeks_computer_network_lecture_notes-2024.3.3.0.dist-info/RECORD
